ssky/__init__.py
ssky/delete.py
ssky/follow.py
ssky/get.py
ssky/login.py
ssky/main.py
ssky/post.py
ssky/post_data_list.py
ssky/profile.py
ssky/profile_list.py
ssky/repost.py
ssky/result.py
ssky/search.py
ssky/ssky_session.py
ssky/thread_data.py
ssky/thread_data_list.py
ssky/unfollow.py
ssky/unrepost.py
ssky/user.py
ssky/util.py
ssky_mcp/__init__.py
ssky_mcp/server.py
ssky-0.2.9.dist-info/METADATA
ssky-0.2.9.dist-info/WHEEL
ssky-0.2.9.dist-info/entry_points.txt
ssky-0.2.9.dist-info/licenses/LICENSE
ssky-0.2.9.dist-info/RECORD
