Metadata-Version: 2.4
Name: ssky
Version: 0.2.9
Summary: Simple bluesky client
License: LICENSE
License-File: LICENSE
Keywords: bluesky,client
Author: SimpleSkyClient Project
Author-email: simpleskypclient@gmail.com
Requires-Python: >=3.12,<3.14
Classifier: License :: Other/Proprietary License
Classifier: Programming Language :: Python :: 3
Classifier: Programming Language :: Python :: 3.12
Classifier: Programming Language :: Python :: 3.13
Requires-Dist: atproto (>=0.0.60,<0.0.61)
Requires-Dist: beautifulsoup4 (>=4.12.3,<5.0.0)
Requires-Dist: fastmcp (>=2.10.0,<3.0.0)
Requires-Dist: pytest (>=8.3.4,<9.0.0)
Requires-Dist: python-dotenv (>=1.0.1,<2.0.0)
Requires-Dist: requests (>=2.32.3,<3.0.0)
Project-URL: Homepage, https://github.com/simpleskyclient/ssky
Project-URL: Repository, https://github.com/simpleskyclient/ssky
